nightskyrunner/__init__.py
nightskyrunner/compare.py
nightskyrunner/config.py
nightskyrunner/config_error.py
nightskyrunner/config_getter.py
nightskyrunner/config_toml.py
nightskyrunner/dotted.py
nightskyrunner/error_info.py
nightskyrunner/factories.py
nightskyrunner/log.py
nightskyrunner/manager.py
nightskyrunner/py.typed
nightskyrunner/runner.py
nightskyrunner/shared_memory.py
nightskyrunner/status.py
nightskyrunner/tests.py
nightskyrunner/version.py
nightskyrunner/wait_interrupts.py
nightskyrunner-0.1.1.dist-info/METADATA
nightskyrunner-0.1.1.dist-info/WHEEL
nightskyrunner-0.1.1.dist-info/RECORD
