Metadata-Version: 2.4
Name: nightskyrunner
Version: 0.1.1
Summary: 
Author: Vincent Berenz
Requires-Python: >=3.12,<4
Classifier: Programming Language :: Python :: 3
Classifier: Programming Language :: Python :: 3.12
Classifier: Programming Language :: Python :: 3.13
Classifier: Programming Language :: Python :: 3.14
Requires-Dist: jinja2 (>=3.1.6,<4.0.0)
Requires-Dist: toml (>=0.10.2,<0.11.0)
Requires-Dist: tomli (>=2.3.0,<3.0.0)
Requires-Dist: tomli-w (>=1.2.0,<2.0.0)
